aiogram3b8_calendar/__init__.py
aiogram3b8_calendar/dialog_calendar.py
aiogram3b8_calendar/simple_calendar.py
aiogram3b8_calendar-0.0.2.dist-info/LICENSE.txt
aiogram3b8_calendar-0.0.2.dist-info/METADATA
aiogram3b8_calendar-0.0.2.dist-info/WHEEL
aiogram3b8_calendar-0.0.2.dist-info/top_level.txt
aiogram3b8_calendar-0.0.2.dist-info/RECORD
