Metadata-Version: 2.1
Name: aiogram3b8-calendar
Version: 0.0.2
Summary: Simple Inline Calendar & Date Selection tool for Aiogram Telegram bots
Home-page: https://github.com/yoworu/aiogram3.0.0b8_calendar/
Download-URL: https://github.com/yoworu/aiogram3.0.0b8_calendar.git
Author: Andrew Nikolabay
Author-email: 
License: MIT
Keywords: Aiogram,Telegram,Bots,Calendar
Classifier: Development Status :: 3 - Alpha
Classifier: Intended Audience :: Developers
Classifier: Topic :: Software Development :: Libraries :: Python Modules
Classifier: License :: OSI Approved :: MIT License
Classifier: Programming Language :: Python :: 3
Classifier: Programming Language :: Python :: 3.6
Classifier: Programming Language :: Python :: 3.7
Classifier: Programming Language :: Python :: 3.8
Classifier: Programming Language :: Python :: 3.9
License-File: LICENSE.txt
Requires-Dist: aiogram (==3.0.0b7)
